yt_transcript_fetcher/__init__.py
yt_transcript_fetcher/api.py
yt_transcript_fetcher/cli.py
yt_transcript_fetcher/exceptions.py
yt_transcript_fetcher/models.py
yt_transcript_fetcher/parsers.py
yt_transcript_fetcher/protobuf.py
yt_transcript_fetcher-1.2.1.dist-info/METADATA
yt_transcript_fetcher-1.2.1.dist-info/WHEEL
yt_transcript_fetcher-1.2.1.dist-info/entry_points.txt
yt_transcript_fetcher-1.2.1.dist-info/licenses/LICENSE
yt_transcript_fetcher-1.2.1.dist-info/RECORD
