Metadata-Version: 2.4
Name: yt-transcript-fetcher
Version: 1.2.1
Summary: This library can be used to fetch transcripts for YouTube videos
Project-URL: Home Page, https://github.com/SootyOwl/yt-transcript-fetcher
Project-URL: Issue Tracker, https://github.com/SootyOwl/yt-transcript-fetcher/issues
Project-URL: Release Notes, https://github.com/SootyOwl/yt-transcript-fetcher/releases
Project-URL: CHANGELOG, https://github.com/SootyOwl/yt-transcript-fetcher/blob/main/CHANGELOG.md
Author-email: Dan Eagle <dan@tyto.cc>
License: MIT
License-File: LICENSE
Keywords: caption,captions,subtitle,subtitles,transcript,transcripts,video,youtube,youtube-api,youtube-subtitles,youtube-transcripts,yt,yt-transcript
Classifier: Development Status :: 4 - Beta
Classifier: Intended Audience :: Developers
Classifier: License :: OSI Approved :: MIT License
Classifier: Operating System :: OS Independent
Classifier: Programming Language :: Python :: 3
Classifier: Programming Language :: Python :: 3.9
Classifier: Programming Language :: Python :: 3.10
Classifier: Programming Language :: Python :: 3.11
Classifier: Programming Language :: Python :: 3.12
Classifier: Programming Language :: Python :: 3.13
Classifier: Topic :: Multimedia :: Video
Classifier: Topic :: Software Development :: Libraries :: Python Modules
Requires-Python: <4.0,>=3.9
Requires-Dist: argcomplete>=3.6.2
Requires-Dist: requests<3.0.0,>=2.32.4
Provides-Extra: build
Requires-Dist: uv~=0.8.14; extra == 'build'
